pyopsview/__init__.py
pyopsview/exceptions.py
pyopsview/resource.py
pyopsview/schema.py
pyopsview/utils.py
pyopsview/v2/__init__.py
pyopsview/v2/client.py
pyopsview/v2/versions.py
pyopsview/v2/config/__init__.py
pyopsview/v2/config/bsmcomponents.py
pyopsview/v2/config/bsmservices.py
pyopsview/v2/config/client.py
pyopsview/v2/config/clusters.py
pyopsview/v2/config/collectors.py
pyopsview/v2/config/flowcollectors.py
pyopsview/v2/config/flowsources.py
pyopsview/v2/config/hashtags.py
pyopsview/v2/config/hostcheckcommands.py
pyopsview/v2/config/hostgroups.py
pyopsview/v2/config/hosticons.py
pyopsview/v2/config/hosts.py
pyopsview/v2/config/hosttemplates.py
pyopsview/v2/config/monitoringservers.py
pyopsview/v2/config/notificationmethods.py
pyopsview/v2/config/roles.py
pyopsview/v2/config/servicechecks.py
pyopsview/v2/config/servicegroups.py
pyopsview/v2/config/sharednotificationprofiles.py
pyopsview/v2/config/tenancies.py
pyopsview/v2/config/timeperiods.py
pyopsview/v2/config/users.py
pyopsview/v2/config/variables.py
pyopsview/v2/schemas/5.3/config/attribute.json
pyopsview/v2/schemas/5.3/config/bsmcomponent.json
pyopsview/v2/schemas/5.3/config/bsmservice.json
pyopsview/v2/schemas/5.3/config/contact.json
pyopsview/v2/schemas/5.3/config/host.json
pyopsview/v2/schemas/5.3/config/hostcheckcommand.json
pyopsview/v2/schemas/5.3/config/hostgroup.json
pyopsview/v2/schemas/5.3/config/hosticon.json
pyopsview/v2/schemas/5.3/config/hosttemplate.json
pyopsview/v2/schemas/5.3/config/keyword.json
pyopsview/v2/schemas/5.3/config/monitoringserver.json
pyopsview/v2/schemas/5.3/config/netflowcollector.json
pyopsview/v2/schemas/5.3/config/netflowsource.json
pyopsview/v2/schemas/5.3/config/notificationmethod.json
pyopsview/v2/schemas/5.3/config/role.json
pyopsview/v2/schemas/5.3/config/servicecheck.json
pyopsview/v2/schemas/5.3/config/servicegroup.json
pyopsview/v2/schemas/5.3/config/sharednotificationprofile.json
pyopsview/v2/schemas/5.3/config/tenancy.json
pyopsview-6.2.3.dist-info/LICENSE
pyopsview-6.2.3.dist-info/METADATA
pyopsview-6.2.3.dist-info/WHEEL
pyopsview-6.2.3.dist-info/top_level.txt
pyopsview-6.2.3.dist-info/RECORD
