Metadata-Version: 2.1
Name: pyopsview
Version: 6.2.3
Summary: Python client for the Opsview API
Home-page: https://github.com/jpgxs/pyopsview
Maintainer: Joshua Griffiths
Maintainer-email: joshua.griffiths@opsview.com
License: UNKNOWN
Download-URL: https://github.com/jpgxs/pyopsview
Platform: UNKNOWN
Requires-Dist: requests (>=2.0.0)
Requires-Dist: six (>=1.0.0)
